skylark/__init__.py
skylark/constants/__init__.py
skylark/constants/constants.py
skylark/core/__init__.py
skylark/core/cab_violence_stream.py
skylark/core/city_wide_stream.py
skylark/core/clients.py
skylark/core/crowd_counting_stream.py
skylark/core/dress_insights_stream.py
skylark/core/ensemble_license_ocr_stream.py
skylark/core/face_detect_stream.py
skylark/core/face_mask_stream.py
skylark/core/face_recog_stream.py
skylark/core/facial_landmark_stream.py
skylark/core/general_violence_stream.py
skylark/core/lie_detection_stream.py
skylark/core/multi_stream.py
skylark/core/night_day_stream.py
skylark/core/pedestrian_detect_stream.py
skylark/core/process_frames.py
skylark/core/streams.py
skylark/core/weapon_detection_stream.py
skylark/core/frame_process/__init__.py
skylark/core/frame_process/test.py
skylark/core/frame_process/utils.py
skylark/core/frame_process/websocket_client.py
skylark/test/__init__.py
skylark/test/frame_test.py
skylark/test/test_frame_client.py
skylark/test/test_websocket_client.py
skylark/utils/__init__.py
skylark/utils/utils.py
skylark_ai-2.0.4.dist-info/LICENSE.txt
skylark_ai-2.0.4.dist-info/METADATA
skylark_ai-2.0.4.dist-info/WHEEL
skylark_ai-2.0.4.dist-info/top_level.txt
skylark_ai-2.0.4.dist-info/RECORD
