Metadata-Version: 2.1
Name: skylark-ai
Version: 2.0.4
Summary: Websocket SDK for Skylark APIs
Home-page: https://github.com/skylarklabsAI/python-sdk
Author: skylarklabs
Author-email: admin@skylarklabs.ai
License: MIT
Platform: UNKNOWN
Requires-Python: >=3.6
License-File: LICENSE.txt
Requires-Dist: websockets
Requires-Dist: sockets
Requires-Dist: asyncio
Requires-Dist: threaded
Requires-Dist: opencv-python
Requires-Dist: numpy
Requires-Dist: pymitter
Requires-Dist: websocket-client
